personal_page_creator/__init__.py
personal_page_creator/__main__.py
personal_page_creator/github_service.py
personal_page_creator/personal_page_creator.py
personal_page_creator/templates/base.html
personal_page_creator/templates/index.template
personal_page_creator/templates/style.template
personal_page_creator-0.0.15.dist-info/LICENSE
personal_page_creator-0.0.15.dist-info/METADATA
personal_page_creator-0.0.15.dist-info/WHEEL
personal_page_creator-0.0.15.dist-info/entry_points.txt
personal_page_creator-0.0.15.dist-info/top_level.txt
personal_page_creator-0.0.15.dist-info/RECORD
